evaluation_metrics/__init__.py
evaluation_metrics/model_evaluation.py
evaluation_metrics-0.1.0.dist-info/LICENSE.txt
evaluation_metrics-0.1.0.dist-info/METADATA
evaluation_metrics-0.1.0.dist-info/WHEEL
evaluation_metrics-0.1.0.dist-info/RECORD
